Workbook

Sheet Tổng quan
A1: ANGI – Từ điển dữ liệu (Data Dictionary)
A4: STT | B4: Schema | C4: Tên bảng | D4: Mô tả bảng | E4: Số trường
A5: 1 | B5: core | C5: roles | D5: Danh mục role: Traveler, Restaurant Owner, Mod, Admin | E5: =COUNTIF(Core!$A:$A,C5) -> 3
A6: 2 | B6: core | C6: users | D6: Tài khoản người dùng (mỗi tài khoản 1 role) | E6: =COUNTIF(Core!$A:$A,C6) -> 15
A7: 3 | B7: core | C7: permissions | D7: Danh mục quyền chi tiết | E7: =COUNTIF(Core!$A:$A,C7) -> 3
A8: 4 | B8: core | C8: role_permissions | D8: Quyền mặc định của từng role | E8: =COUNTIF(Core!$A:$A,C8) -> 2
A9: 5 | B9: core | C9: user_permissions | D9: Ghi đè quyền cho từng user (Admin quản lý quyền của Mod) | E9: =COUNTIF(Core!$A:$A,C9) -> 5
A10: 6 | B10: core | C10: user_external_logins | D10: Liên kết đăng nhập Google | E10: =COUNTIF(Core!$A:$A,C10) -> 5
A11: 7 | B11: core | C11: user_tokens | D11: Token xác minh email và reset mật khẩu | E11: =COUNTIF(Core!$A:$A,C11) -> 7
A12: 8 | B12: core | C12: user_sessions | D12: Phiên đăng nhập / refresh token | E12: =COUNTIF(Core!$A:$A,C12) -> 8
A13: 9 | B13: core | C13: media_files | D13: File upload dùng chung (ảnh, giấy tờ) | E13: =COUNTIF(Core!$A:$A,C13) -> 7
A14: 10 | B14: core | C14: restaurants | D14: Nhà hàng (mỗi Owner 1 nhà hàng) | E14: =COUNTIF(Core!$A:$A,C14) -> 24
A15: 11 | B15: core | C15: restaurant_images | D15: Ảnh của nhà hàng | E15: =COUNTIF(Core!$A:$A,C15) -> 3
A16: 12 | B16: core | C16: restaurant_business_hours | D16: Giờ mở cửa theo ngày, nhiều ca/ngày | E16: =COUNTIF(Core!$A:$A,C16) -> 5
... A45: 41 | B45: core | C45: agent_proposals | D45: Proposal bất biến và kết quả confirm roadmap. | E45: =COUNTIF(Core!$A:$A,C45) -> 16
A46: 42 | B46: recommendation | C46: algorithm_configs | D46: Cấu hình thuật toán có phiên bản | E46: =COUNTIF(Recommendation!$A:$A,C46) -> 5
A47: 43 | B47: recommendation | C47: survey_option_vectors | D47: Quy lựa chọn khảo sát thành vector 12 chiều | E47: =COUNTIF(Recommendation!$A:$A,C47) -> 4
A48: 44 | B48: recommendation | C48: dish_vectors | D48: Vector 12 chiều của món do AI sinh | E48: =COUNTIF(Recommendation!$A:$A,C48) -> 15
A49: 45 | B49: recommendation | C49: user_preference_vectors | D49: Vector user và bộ đếm m, N_total | E49: =COUNTIF(Recommendation!$A:$A,C49) -> 10
A50: 46 | B50: recommendation | C50: user_dish_scores | D50: Implicit S, n, N_i theo cặp user-món | E50: =COUNTIF(Recommendation!$A:$A,C50) -> 9
A51: 47 | B51: recommendation | C51: dish_stats | D51: Like/dislike cộng đồng cho Wilson | E51: =COUNTIF(Recommendation!$A:$A,C51) -> 4
A52: 48 | B52: recommendation | C52: interaction_events | D52: Log like/dislike append-only (nguồn sự thật) | E52: =COUNTIF(Recommendation!$A:$A,C52) -> 10
A53: 49 | B53: recommendation | C53: recommendation_logs | D53: Mỗi lần gọi /recommendations | E53: =COUNTIF(Recommendation!$A:$A,C53) -> 11
A54: 50 | B54: recommendation | C54: recommendation_items | D54: Điểm từng tầng của từng món trong một lần gợi ý | E54: =COUNTIF(Recommendation!$A:$A,C54) -> 14
C56: Tổng số trường | E56: =SUM(E5:E54) -> 426
C57: Số bảng core | E57: =COUNTIF(B5:B54,"core") -> 41
C58: Số bảng recommendation | E58: =COUNTIF(B5:B54,"recommendation") -> 9
A60: Thay đổi Ver1.1 (06/10/2026)
A61: 1 | C61: restaurants.latitude / longitude chuyển thành NOT NULL (OWN-01 vốn đã bắt buộc). Cần cho lọc quán gần và tính lộ trình.
A62: 2 | C62: roadmaps thêm origin_mode (none | pinned | gps), origin_latitude, origin_longitude, origin_label: 3 cách chọn điểm xuất phát khi lập roadmap. Chỉ lưu tọa độ khi pinned.
A63: 3 | C63: roadmap_generation_jobs.input ghi thêm điểm xuất phát và bán kính đã dùng khi sinh.
A64: 4 | C64: Không lưu km / thời gian di chuyển: backend gọi Mapbox Directions khi app cần (RM-14 trong API Design Ver1.7) và cache trong bộ nhớ.
A66: Thay đổi Ver1.2 (07/10/2026)
A67: 1 | C67: recommendation.user_dish_scores thêm implicit_raw (tổng thô r); implicit_score tính từ r. Theo Recommendation_System_Design_Ver1.1 mục 3.2: lưu giá trị đã nén rồi nén tiếp làm Implicit kẹt quanh 0,527.
A68: 2 | C68: user_preference_vectors.vec: người chưa có vector thì like/dislike đầu tiên tạo vector = ±β_u·Dish.
A69: 3 | C69: algorithm_configs.params: gamma = 0 cho tới giai đoạn 3 (UCB).
A70: 4 | C70: recommendation_items.rank: món bằng điểm giữ thứ tự backend gửi.
A71: 5 | C71: Sheet Recommendation ghi rõ CHECK, unique index và index của schema recommendation (khớp migration 0001 của angi-reco); ô mô tả interaction_events.event_uuid bắt đầu bằng "=" bị Excel coi là công thức, ghi lại thành chữ.
A72: 6 | C72: Cột Khóa của sheet Core ghi ON DELETE CASCADE (dòng con thuộc về dòng cha) hoặc ON DELETE SET NULL; khóa ngoại không ghi là RESTRICT. Khớp migration của backend.
A1001: Chat-only contract 2026-10-27 | B1001: UI chỉ chat và Gửi. Request chuẩn chỉ cần content. clientMessageId và expectedConversationVersion là tùy chọn; null/bỏ trống để backend tự cấp ID và dùng version đang khóa. Backend nhận diện thao tác; câu lưu rõ ràng gọi chung code confirm, ghi roadmap/proposal/transcript/replay response trong transaction có lease. Đồng ý đơn lẻ chỉ xác nhận pendingStateChange. Reset tách roadmap, không xóa dữ liệu chính thức. Metadata server-only pendingStateChange/sourceRoadmapVersion/historyStartSequence nằm trong JSONB state hiện có, không thêm cột/migration. AGENT-04 và các trường tùy chọn cũ giữ tương thích.
A1002: Agent availability 2026-10-28 | B1002: Agent:LlmTimeoutSeconds defaults to 60 per call, capped by the 90-second turn deadline; lease remains 120 seconds. MaxLlmCalls defaults to 8. Retry upstream 500/502/503 at most twice with backoff; retry a short per-minute limit only with provider guidance and sufficient turn time. Never retry daily quota exhaustion, timeout, network, authentication, refusal or truncation. Allow one schema/operation repair. Disable tools after the round ceiling. Parse object/array Gemini errors and RetryInfo. Provider rate/quota failures return HTTP 429 AGENT_UNAVAILABLE; other provider failures return HTTP 503 AGENT_UNAVAILABLE. Application admission limits remain HTTP 429 AGENT_RATE_LIMITED. Preserve Retry-After, caller cancellation and the previous preview. Log only safe fixed labels, status and timings, never prompts, keys or raw error bodies. No database schema change.
A1003: Agent lifecycle stabilization 2026-10-29 | B1003: Current lifecycle: startDate is optional; require province, duration and budget. Return complete snapshots ordered by day, meal, sortOrder and stable item key, including GET of older proposals. Broad candidate searches never widen mutation scope or force replacing unchanged side dishes. On explicit pending-constraint consent, regenerate in the same turn using the exact accepted state; temporary tool filters do not require fresh consent. Support explicit chot/save aliases; a review-before-save request never commits. Do not replay an obsolete committed preview as a new save after state changes. Catalog-backed tastes only; unsupported sweet/spicy preferences remain notes.

Sheet Core
A1: Tên bảng | B1: Tên trường | C1: Kiểu dữ liệu | D1: Not null / Nullable | E1: Mô tả trường | F1: Khóa | G1: Mặc định
A2: roles — Danh mục role: Traveler, Restaurant Owner, Mod, Admin
A3: roles | B3: id | C3: smallint | D3: NOT NULL | E3: Khóa chính role | F3: PK
A4: roles | B4: code | C4: character varying(30) | D4: NOT NULL | E4: TRAVELER, RESTAURANT_OWNER, MOD, ADMIN | F4: UK
A5: roles | B5: name | C5: character varying(100) | D5: NOT NULL | E5: Tên hiển thị của role
A6: users — Tài khoản người dùng (mỗi tài khoản 1 role)
A7: users | B7: id | C7: integer | D7: NOT NULL | E7: Khóa chính người dùng; cũng là user_id bên recommendation | F7: PK
A8: users | B8: email | C8: citext | D8: NOT NULL | E8: Email đăng nhập, không phân biệt hoa thường; duy nhất trong các tài khoản chưa xóa | F8: UK (deleted_at IS NULL)
A9: users | B9: role_id | C9: smallint | D9: NOT NULL | E9: Role duy nhất của tài khoản (Traveler, Restaurant Owner, Mod, Admin) | F9: FK → roles
A10: users | B10: password_hash | C10: text | D10: NULL | E10: NULL nếu chỉ đăng nhập Google
A11: users | B11: display_name | C11: character varying(100) | D11: NOT NULL | E11: Tên hiển thị
A12: users | B12: avatar_media_id | C12: bigint | D12: NULL | E12: Ảnh đại diện (media_files, purpose = avatar); NULL = chưa có ảnh | F12: FK → media_files
A13: users | B13: phone | C13: character varying(20) | D13: NULL | E13: Số điện thoại
A14: users | B14: bio | C14: character varying(500) | D14: NULL | E14: Giới thiệu ngắn
A15: users | B15: email_verified_at | C15: timestamp with time zone | D15: NULL | E15: Thời điểm xác minh email; NULL = chưa xác minh
A16: users | B16: status | C16: character varying(20) | D16: NOT NULL | E16: Trạng thái tài khoản: pending_verification, active, suspended, banned, deactivated | G16: "pending_verification"
A17: users | B17: suspended_until | C17: timestamp with time zone | D17: NULL | E17: Chỉ dùng khi status = 'suspended'
A18: users | B18: last_login_at | C18: timestamp with time zone | D18: NULL | E18: Lần đăng nhập gần nhất
A19: users | B19: created_at | C19: timestamp with time zone | D19: NOT NULL | E19: Thời điểm tạo | G19: now()
A20: users | B20: updated_at | C20: timestamp with time zone | D20: NOT NULL | E20: Thời điểm cập nhật gần nhất | G20: now()
A21: users | B21: deleted_at | C21: timestamp with time zone | D21: NULL | E21: Thời điểm xóa mềm; NULL = chưa xóa
A22: permissions — Danh mục quyền chi tiết
A23: permissions | B23: id | C23: smallint | D23: NOT NULL | E23: Khóa chính quyền | F23: PK
A24: permissions | B24: code | C24: character varying(60) | D24: NOT NULL | E24: Vd: USER_BAN, RESTAURANT_VERIFY, MENU_APPROVE, BLOG_MODERATE | F24: UK
A25: permissions | B25: description | C25: character varying(255) | D25: NULL | E25: Mô tả quyền
A26: role_permissions — Quyền mặc định của từng role
A27: role_permissions | B27: role_id | C27: smallint | D27: NOT NULL | E27: Role được cấp quyền | F27: PK (ghép), FK → roles (ON DELETE CASCADE)
A28: role_permissions | B28: permission_id | C28: smallint | D28: NOT NULL | E28: Quyền mặc định của role | F28: PK (ghép), FK → permissions (ON DELETE CASCADE)
A29: user_permissions — Ghi đè quyền cho từng user (Admin quản lý quyền của Mod)
A30: user_permissions | B30: user_id | C30: integer | D30: NOT NULL | E30: User (thường là Mod) được ghi đè quyền | F30: PK (ghép), FK → users (ON DELETE CASCADE)
A31: user_permissions | B31: permission_id | C31: smallint | D31: NOT NULL | E31: Quyền bị ghi đè | F31: PK (ghép), FK → permissions (ON DELETE CASCADE)
A32: user_permissions | B32: effect | C32: character varying(5) | D32: NOT NULL | E32: allow = cấp thêm, deny = thu hồi so với quyền của role | G32: "allow"
A33: user_permissions | B33: granted_by | C33: integer | D33: NULL | E33: Admin thực hiện | F33: FK → users
A34: user_permissions | B34: granted_at | C34: timestamp with time zone | D34: NOT NULL | E34: Thời điểm cấp/thu | G34: now()
A35: user_external_logins — Liên kết đăng nhập Google
A36: user_external_logins | B36: id | C36: bigint | D36: NOT NULL | E36: Khóa chính | F36: PK
A37: user_external_logins | B37: user_id | C37: integer | D37: NOT NULL | E37: Tài khoản ANGI được liên kết | F37: UK (ghép), FK → users (ON DELETE CASCADE)
A38: user_external_logins | B38: provider | C38: character varying(20) | D38: NOT NULL | E38: Nhà cung cấp đăng nhập (hiện chỉ google) | F38: UK (ghép)
A39: user_external_logins | B39: provider_user_id | C39: character varying(255) | D39: NOT NULL | E39: Id người dùng phía Google (claim "sub") | F39: UK (ghép)
A40: user_external_logins | B40: linked_at | C40: timestamp with time zone | D40: NOT NULL | E40: Thời điểm liên kết | G40: now()
A41: user_tokens — Token xác minh email và reset mật khẩu
A42: user_tokens | B42: id | C42: bigint | D42: NOT NULL | E42: Khóa chính | F42: PK
A43: user_tokens | B43: user_id | C43: integer | D43: NOT NULL | E43: Chủ token | F43: FK → users (ON DELETE CASCADE)
A44: user_tokens | B44: purpose | C44: character varying(20) | D44: NOT NULL | E44: Mục đích: email_verify hoặc password_reset
A45: user_tokens | B45: token_hash | C45: text | D45: NOT NULL | E45: Hash của token/mã gửi qua email (không lưu bản gốc) | F45: UK
A46: user_tokens | B46: expires_at | C46: timestamp with time zone | D46: NOT NULL | E46: Hết hạn
A47: user_tokens | B47: used_at | C47: timestamp with time zone | D47: NULL | E47: Thời điểm đã dùng; NULL = chưa dùng (dùng 1 lần)
A48: user_tokens | B48: created_at | C48: timestamp with time zone | D48: NOT NULL | E48: Thời điểm tạo | G48: now()
A49: user_sessions — Phiên đăng nhập / refresh token
A50: user_sessions | B50: id | C50: bigint | D50: NOT NULL | E50: Khóa chính phiên; cũng là claim sid trong access token của phiên này | F50: PK
A51: user_sessions | B51: user_id | C51: integer | D51: NOT NULL | E51: Chủ phiên | F51: FK → users (ON DELETE CASCADE)
A52: user_sessions | B52: refresh_token_hash | C52: text | D52: NOT NULL | E52: Hash refresh token | F52: UK
A53: user_sessions | B53: user_agent | C53: character varying(500) | D53: NULL | E53: Thiết bị/trình duyệt
A54: user_sessions | B54: ip_address | C54: inet | D54: NULL | E54: IP đăng nhập
A55: user_sessions | B55: created_at | C55: timestamp with time zone | D55: NOT NULL | E55: Thời điểm tạo | G55: now()
A56: user_sessions | B56: expires_at | C56: timestamp with time zone | D56: NOT NULL | E56: Hết hạn phiên
A57: user_sessions | B57: revoked_at | C57: timestamp with time zone | D57: NULL | E57: Thời điểm thu hồi (đăng xuất, đổi mật khẩu); NULL = còn hiệu lực
A58: media_files — File upload dùng chung (ảnh, giấy tờ)
A59: media_files | B59: id | C59: bigint | D59: NOT NULL | E59: Khóa chính file | F59: PK
A60: media_files | B60: uploader_id | C60: integer | D60: NULL | E60: Người upload | F60: FK → users
A61: media_files | B61: storage_key | C61: text | D61: NOT NULL | E61: Key trên S3/Cloudinary/... | F61: UK
A62: media_files | B62: url | C62: text | D62: NOT NULL | E62: URL công khai của file
A63: media_files | B63: mime_type | C63: character varying(100) | D63: NOT NULL | E63: Kiểu file (image/jpeg, application/pdf...)
A64: media_files | B64: size_bytes | C64: bigint | D64: NULL | E64: Dung lượng (byte)
A65: media_files | B65: created_at | C65: timestamp with time zone | D65: NOT NULL | E65: Thời điểm tạo | G65: now()
A66: restaurants — Nhà hàng (mỗi Owner 1 nhà hàng)
A67: restaurants | B67: id | C67: bigint | D67: NOT NULL | E67: Khóa chính nhà hàng | F67: PK
A68: restaurants | B68: owner_id | C68: integer | D68: NOT NULL | E68: Restaurant Owner quản lý (mỗi Owner tối đa 1 nhà hàng chưa xóa) | F68: UK (deleted_at IS NULL), FK → users
A69: restaurants | B69: name | C69: character varying(200) | D69: NOT NULL | E69: Tên nhà hàng
A70: restaurants | B70: slug | C70: character varying(220) | D70: NOT NULL | E70: Slug dùng trên URL | F70: UK (deleted_at IS NULL)
A71: restaurants | B71: description | C71: text | D71: NULL | E71: Mô tả nhà hàng
A72: restaurants | B72: phone | C72: character varying(20) | D72: NULL | E72: Số điện thoại liên hệ
A73: restaurants | B73: email | C73: citext | D73: NULL | E73: Email liên hệ
A74: restaurants | B74: website | C74: text | D74: NULL | E74: Website/fanpage
A75: restaurants | B75: address_line | C75: character varying(255) | D75: NOT NULL | E75: Số nhà, tên đường
A76: restaurants | B76: ward | C76: character varying(100) | D76: NULL | E76: Phường/xã, tên theo provinces.open-api.vn V2 (địa giới từ 01/07/2025, không còn quận/huyện)
A77: restaurants | B77: province_name | C77: character varying(100) | D77: NULL | E77: Tỉnh/thành, tên theo provinces.open-api.vn V2 (địa giới từ 01/07/2025, không còn quận/huyện)
A78: restaurants | B78: latitude | C78: numeric(9,6) | D78: NOT NULL | E78: Vĩ độ (Owner chấm trên bản đồ khi đăng ký). Dùng lọc quán gần và tính lộ trình
A79: restaurants | B79: longitude | C79: numeric(9,6) | D79: NOT NULL | E79: Kinh độ (Owner chấm trên bản đồ khi đăng ký). Dùng lọc quán gần và tính lộ trình
A80: restaurants | B80: price_level | C80: smallint | D80: NULL | E80: Mức giá 1 đến 4 ($ đến $$$$)
A81: restaurants | B81: cover_media_id | C81: bigint | D81: NULL | E81: Ảnh bìa nhà hàng | F81: FK → media_files
A82: restaurants | B82: verification_status | C82: character varying(20) | D82: NOT NULL | E82: Trạng thái xác minh: unverified, pending, verified, rejected | G82: "unverified"
A83: restaurants | B83: operating_status | C83: character varying(20) | D83: NOT NULL | E83: Trạng thái hoạt động do Owner đặt: open, temporarily_closed, permanently_closed | G83: "open"
A84: restaurants | B84: moderation_status | C84: character varying(20) | D84: NOT NULL | E84: Trạng thái kiểm duyệt do Mod đặt: visible, hidden, suspended | G84: "visible"
A85: restaurants | B85: rating_avg | C85: numeric(3,2) | D85: NOT NULL | E85: Denormalized từ restaurant_reviews | G85: 0
A86: restaurants | B86: rating_count | C86: integer | D86: NOT NULL | E86: Số review đang hiển thị (denormalized) | G86: 0
A87: restaurants | B87: created_at | C87: timestamp with time zone | D87: NOT NULL | E87: Thời điểm tạo | G87: now()
A88: restaurants | B88: updated_at | C88: timestamp with time zone | D88: NOT NULL | E88: Thời điểm cập nhật gần nhất | G88: now()
A89: restaurants | B89: deleted_at | C89: timestamp with time zone | D89: NULL | E89: Thời điểm xóa mềm; NULL = chưa xóa
A90: restaurant_images — Ảnh của nhà hàng
A91: restaurant_images | B91: restaurant_id | C91: bigint | D91: NOT NULL | E91: Nhà hàng | F91: PK (ghép), FK → restaurants (ON DELETE CASCADE)
A92: restaurant_images | B92: media_id | C92: bigint | D92: NOT NULL | E92: Ảnh | F92: PK (ghép), FK → media_files
A93: restaurant_images | B93: sort_order | C93: smallint | D93: NOT NULL | E93: Thứ tự hiển thị | G93: 0
A94: restaurant_business_hours — Giờ mở cửa theo ngày, nhiều ca/ngày
A95: restaurant_business_hours | B95: id | C95: bigint | D95: NOT NULL | E95: Khóa chính | F95: PK
A96: restaurant_business_hours | B96: restaurant_id | C96: bigint | D96: NOT NULL | E96: Nhà hàng | F96: UK (ghép), FK → restaurants (ON DELETE CASCADE)
A97: restaurant_business_hours | B97: day_of_week | C97: smallint | D97: NOT NULL | E97: Thứ trong tuần: 0 = Chủ nhật ... 6 = Thứ bảy | F97: UK (ghép)
A98: restaurant_business_hours | B98: open_time | C98: time without time zone | D98: NOT NULL | E98: Giờ mở cửa của ca | F98: UK (ghép)
A99: restaurant_business_hours | B99: close_time | C99: time without time zone | D99: NOT NULL | E99: Close_time < open_time nghĩa là qua đêm
A100: restaurant_verifications — Các lần nộp xác minh nhà hàng
...

Sheet Recommendation
A1: Tên bảng | B1: Tên trường | C1: Kiểu dữ liệu | D1: Not null / Nullable | E1: Mô tả trường | F1: Khóa | G1: Mặc định
A2: algorithm_configs — Cấu hình thuật toán có phiên bản
A3: algorithm_configs | B3: config_version | C3: integer | D3: NOT NULL | E3: Số phiên bản cấu hình | F3: PK
A4: algorithm_configs | B4: params | C4: jsonb | D4: NOT NULL | E4: {"beta_u":0.03,"beta_s":0.03,"k":5,"k_prime":5,"z":1.96,"gamma":0,"explicit_norm":"minmax_cosine","ontology_version":1}. gamma = 0 cho tới khi làm UCB (giai đoạn 3), sau đó thêm config_version mới với gamma = 0.1
A5: algorithm_configs | B5: is_active | C5: boolean | D5: NOT NULL | E5: Cấu hình đang dùng (chỉ 1 dòng true). Unique index một phần WHERE is_active | G5: false
A6: algorithm_configs | B6: note | C6: text | D6: NULL | E6: Ghi chú
A7: algorithm_configs | B7: created_at | C7: timestamp with time zone | D7: NOT NULL | E7: Thời điểm tạo | G7: now()
A8: survey_option_vectors — Quy lựa chọn khảo sát thành vector 12 chiều
A9: survey_option_vectors | B9: option_code | C9: character varying(50) | D9: NOT NULL | E9: Mã lựa chọn khảo sát do app gửi lên (bộ câu hỏi cố định ở FE) | F9: PK
A10: survey_option_vectors | B10: vec | C10: vector(12) | D10: NOT NULL | E10: Các chiều không liên quan để 0. Được phép toàn 0 (vd lựa chọn “không ăn cay”)
A11: survey_option_vectors | B11: dim_mask | C11: vector(12) | D11: NOT NULL | E11: 1 ở chiều mà option này có ý kiến, 0 ở chiều còn lại. CHECK: khác vector 0 (lựa chọn phải chạm ít nhất 1 chiều)
A12: survey_option_vectors | B12: updated_at | C12: timestamp with time zone | D12: NOT NULL | E12: Thời điểm cập nhật gần nhất | G12: now()
A13: dish_vectors — Vector 12 chiều của món do AI sinh
A14: dish_vectors | B14: dish_id | C14: integer | D14: NOT NULL | E14: Món (= core.dishes.id, tham chiếu mềm) | F14: PK
A15: dish_vectors | B15: vec | C15: vector(12) | D15: NULL | E15: NULL khi chưa sinh được / failed. CHECK: khác vector 0; status = ready thì vec khác NULL
A16: dish_vectors | B16: raw_ai_output | C16: jsonb | D16: NULL | E16: JSON gốc AI trả về
A17: dish_vectors | B17: source_hash | C17: character(64) | D17: NOT NULL | E17: Sha256(name + description ...)
A18: dish_vectors | B18: model_name | C18: character varying(100) | D18: NULL | E18: Model AI sinh vector
A19: dish_vectors | B19: ontology_version | C19: smallint | D19: NOT NULL | E19: Phiên bản ontology (12 chiều = 1) | G19: 1
A20: dish_vectors | B20: status | C20: character varying(10) | D20: NOT NULL | E20: pending, ready, failed. CHECK theo giá trị trên. Index một phần WHERE status <> 'ready' cho vòng lặp nền | G20: "pending"
A21: dish_vectors | B21: attempt_count | C21: smallint | D21: NOT NULL | E21: Số lần sinh vector đã thử. CHECK: ≥ 0 | G21: 0
A22: dish_vectors | B22: last_error | C22: text | D22: NULL | E22: Lỗi lần sinh gần nhất
A23: dish_vectors | B23: is_active | C23: boolean | D23: NOT NULL | E23: False khi backend xóa/ẩn món | G23: true
A24: dish_vectors | B24: name | C24: character varying(200) | D24: NULL | E24: Tên món đã nhận, dùng để sinh lại vector khi failed
A25: dish_vectors | B25: description | C25: text | D25: NULL | E25: Mô tả món đã nhận
A26: dish_vectors | B26: last_event_at | C26: timestamp with time zone | D26: NULL | E26: Occurred_at của sự kiện mới nhất đã áp dụng; sự kiện cũ hơn (đến trễ) bị bỏ qua
A27: dish_vectors | B27: created_at | C27: timestamp with time zone | D27: NOT NULL | E27: Thời điểm tạo | G27: now()
A28: dish_vectors | B28: updated_at | C28: timestamp with time zone | D28: NOT NULL | E28: Thời điểm cập nhật gần nhất | G28: now()
A29: user_preference_vectors — Vector user và bộ đếm m, N_total
A30: user_preference_vectors | B30: user_id | C30: integer | D30: NOT NULL | E30: User (= core.users.id, tham chiếu mềm) | F30: PK
A31: user_preference_vectors | B31: initial_vec | C31: vector(12) | D31: NULL | E31: Từ khảo sát; NULL nếu chưa khảo sát. CHECK: khác vector 0
A32: user_preference_vectors | B32: vec | C32: vector(12) | D32: NULL | E32: Cập nhật online. NULL = chưa có (Explicit = 0). Không lưu vector 0: chưa có vector thì coi User_old = 0, like đầu tiên tạo vector = β_u·Dish, dislike đầu tiên tạo vector = −β_u·Dish. CHECK: khác vector 0
A33: user_preference_vectors | B33: survey_answer_count | C33: integer | D33: NOT NULL | E33: q = số câu trả lời khảo sát. CHECK: survey_answer_count, feedback_count, total_shown ≥ 0 | G33: 0
A34: user_preference_vectors | B34: feedback_count | C34: integer | D34: NOT NULL | E34: Số lần like/dislike | G34: 0
A35: user_preference_vectors | B35: total_interactions | C35: integer | D35: NULL | E35: m = q + số like/dislike (cột tính tự động) | G35: (cột tính toán)
A36: user_preference_vectors | B36: total_shown | C36: bigint | D36: NOT NULL | E36: N_total = tổng số lần các món được hiển thị cho user | G36: 0
A37: user_preference_vectors | B37: survey_payload | C37: jsonb | D37: NULL | E37: Câu trả lời thô nhận được
A38: user_preference_vectors | B38: survey_at | C38: timestamp with time zone | D38: NULL | E38: Khác NULL => đã khảo sát; khảo sát chỉ nhận 1 lần (409 nếu gửi lại)
A39: user_preference_vectors | B39: updated_at | C39: timestamp with time zone | D39: NOT NULL | E39: Thời điểm cập nhật gần nhất | G39: now()
A40: user_dish_scores — Implicit S, n, N_i theo cặp user-món
A41: user_dish_scores | B41: user_id | C41: integer | D41: NOT NULL | E41: User (= core.users.id) | F41: PK (ghép)
A42: user_dish_scores | B42: dish_id | C42: integer | D42: NOT NULL | E42: Món (= core.dishes.id) | F42: PK (ghép)
A43: user_dish_scores | B43: implicit_raw | C43: real | D43: NOT NULL | E43: r = tổng β_s·w của các lần like/dislike, không nén. Implicit tính từ cột này | G43: 0
A44: user_dish_scores | B44: implicit_score | C44: real | D44: NOT NULL | E44: Implicit = 0,5 + 0,5·r/(1+|r|), tính lại từ implicit_raw mỗi lần cập nhật (không nén chồng lên giá trị cũ). CHECK: 0 ≤ implicit_score ≤ 1 | G44: 0.5
A45: user_dish_scores | B45: interaction_count | C45: integer | D45: NOT NULL | E45: n = số lần user like/dislike món này. CHECK: interaction_count, shown_count ≥ 0 | G45: 0
A46: user_dish_scores | B46: shown_count | C46: integer | D46: NOT NULL | E46: N_i = số lần món được hiển thị cho user | G46: 0
A47: user_dish_scores | B47: last_feedback | C47: smallint | D47: NULL | E47: Phiếu hiện tại trong dish_stats. CHECK: 1 (like) hoặc -1 (dislike)
A48: user_dish_scores | B48: last_feedback_at | C48: timestamp with time zone | D48: NULL | E48: Thời điểm phản hồi gần nhất
A49: user_dish_scores | B49: updated_at | C49: timestamp with time zone | D49: NOT NULL | E49: Thời điểm cập nhật gần nhất | G49: now()
A50: dish_stats — Like/dislike cộng đồng cho Wilson
A51: dish_stats | B51: dish_id | C51: integer | D51: NOT NULL | E51: Món (= core.dishes.id, tham chiếu mềm) | F51: PK
A52: dish_stats | B52: like_count | C52: integer | D52: NOT NULL | E52: Số user đang like (mỗi user 1 phiếu theo phản hồi gần nhất). CHECK: like_count, dislike_count ≥ 0 | G52: 0
A53: dish_stats | B53: dislike_count | C53: integer | D53: NOT NULL | E53: Số user đang dislike | G53: 0
A54: dish_stats | B54: updated_at | C54: timestamp with time zone | D54: NOT NULL | E54: Thời điểm cập nhật gần nhất | G54: now()
A55: interaction_events — Log like/dislike append-only (nguồn sự thật)
A56: interaction_events | B56: id | C56: bigint | D56: NOT NULL | E56: Khóa chính | F56: PK
A57: interaction_events | B57: event_uuid | C57: uuid | D57: NOT NULL | E57: Bằng core.dish_feedbacks.event_uuid, chống ghi trùng khi backend retry | F57: UK
A58: interaction_events | B58: user_id | C58: integer | D58: NOT NULL | E58: User (= core.users.id). Index (user_id, occurred_at) để replay theo user
A59: interaction_events | B59: dish_id | C59: integer | D59: NOT NULL | E59: Món (= core.dishes.id)
A60: interaction_events | B60: event_type | C60: character varying(10) | D60: NOT NULL | E60: like hoặc dislike. CHECK theo giá trị trên
A61: interaction_events | B61: w | C61: smallint | D61: NOT NULL | E61: +1 (like) hoặc -1 (dislike). CHECK: like đi với +1, dislike đi với -1
A62: interaction_events | B62: request_id | C62: uuid | D62: NULL | E62: Recommendation_logs.request_id nếu có
A63: interaction_events | B63: config_version | C63: integer | D63: NULL | E63: Cấu hình thuật toán lúc xử lý | F63: FK → algorithm_configs
A64: interaction_events | B64: occurred_at | C64: timestamp with time zone | D64: NOT NULL | E64: Thời điểm user bấm (backend gửi)
A65: interaction_events | B65: received_at | C65: timestamp with time zone | D65: NOT NULL | E65: Thời điểm reco nhận | G65: now()
A66: recommendation_logs — Mỗi lần gọi /recommendations
A67: recommendation_logs | B67: request_id | C67: uuid | D67: NOT NULL | E67: Khóa chính lần gợi ý, trả về cho backend | F67: PK | G67: gen_random_uuid()
A68: recommendation_logs | B68: user_id | C68: integer | D68: NOT NULL | E68: User được gợi ý. Index (user_id, created_at)
A69: recommendation_logs | B69: config_version | C69: integer | D69: NOT NULL | E69: Cấu hình thuật toán đã dùng | F69: FK → algorithm_configs
A70: recommendation_logs | B70: context | C70: character varying(20) | D70: NOT NULL | E70: list, home, roll, roadmap_manual, roadmap_ai. CHECK theo giá trị trên | G70: "list"
A71: recommendation_logs | B71: m | C71: integer | D71: NOT NULL | E71: m = tổng tương tác của user lúc gợi ý
A72: recommendation_logs | B72: n_total | C72: bigint | D72: NOT NULL | E72: N_total lúc gợi ý
A73: recommendation_logs | B73: delta | C73: real | D73: NOT NULL | E73: Δ = m/(m+k')
A74: recommendation_logs | B74: candidate_count | C74: integer | D74: NOT NULL | E74: Số món ứng viên backend gửi
A75: recommendation_logs | B75: top_k | C75: integer | D75: NOT NULL | E75: Số món trả về
A76: recommendation_logs | B76: latency_ms | C76: integer | D76: NULL | E76: Thời gian xử lý (ms)
A77: recommendation_logs | B77: created_at | C77: timestamp with time zone | D77: NOT NULL | E77: Thời điểm tạo | G77: now()
A78: recommendation_items — Điểm từng tầng của từng món trong một lần gợi ý
A79: recommendation_items | B79: request_id | C79: uuid | D79: NOT NULL | E79: Lần gợi ý | F79: PK (ghép), FK → recommendation_logs (ON DELETE CASCADE)
A80: recommendation_items | B80: dish_id | C80: integer | D80: NOT NULL | E80: Món ứng viên | F80: PK (ghép)
A81: recommendation_items | B81: rank | C81: integer | D81: NOT NULL | E81: Thứ hạng trong toàn bộ tập ứng viên; bằng điểm thì giữ thứ tự backend gửi (đã sắp theo rating quán)
A82: recommendation_items | B82: is_returned | C82: boolean | D82: NOT NULL | E82: Nằm trong top_k trả về backend
A83: recommendation_items | B83: cosine_sim | C83: real | D83: NULL | E83: NULL nếu user chưa có vector
A84: recommendation_items | B84: explicit_score | C84: real | D84: NOT NULL | E84: Explicit = MinMax của cosine trên tập ứng viên
A85: recommendation_items | B85: implicit_score | C85: real | D85: NOT NULL | E85: Implicit S tại thời điểm gợi ý
A86: recommendation_items | B86: alpha | C86: real | D86: NOT NULL | E86: α = n/(n+k)
A87: recommendation_items | B87: personalized | C87: real | D87: NOT NULL | E87: (1−α)·Explicit + α·Implicit
A88: recommendation_items | B88: wilson | C88: real | D88: NOT NULL | E88: Pooled Wilson Score
A89: recommendation_items | B89: final_score | C89: real | D89: NOT NULL | E89: Δ·Personalized + (1−Δ)·Wilson
A90: recommendation_items | B90: exploration | C90: real | D90: NOT NULL | E90: Exploration Score (UCB, SoftSign)
A91: recommendation_items | B91: recommend_score | C91: real | D91: NOT NULL | E91: (1−γ)·Final + γ·Exploration, dùng để xếp hạng
A92: recommendation_items | B92: shown_at | C92: timestamp with time zone | D92: NULL | E92: Lần đầu món này hiển thị cho user (POST /impressions); NULL = chưa thấy
